{
  "gespeichert_am": "2026-04-11T21:05:26.186Z",
  "produkte": {
    "schlawiner_gesamt_stueck": 11142,
    "schlawiner_gesamt_bleche": 232.13,
    "schlawiner_klassisch_stueck": 2655,
    "schlawiner_kuerbis_stueck": 818,
    "schlawiner_sonnen_stueck": 678,
    "schlawiner_mohn_stueck": 299,
    "schlawiner_koerner_stueck": 763,
    "schlawiner_sesam_stueck": 338,
    "schlawiner_kuerbiskaese_stueck": 55,
    "schlawiner_loewen_stueck": 675,
    "schlawiner_stange3_stueck": 24,
    "schlawiner_stange5_stueck": 5,
    "schlawiner_brot6_stueck": 29,
    "schlawiner_kuestange3_stueck": 15,
    "schlawiner_sostange3_stueck": 15,
    "schlawiner_gemstange3_stueck": 13,
    "schlawiner_loewenstange_stueck": 15,
    "schlawiner_kuestange5_stueck": 0
  }
}